reddit_scraper/__init__.py
reddit_scraper/reddit_scraper.py
reddit_scraper/models/__init__.py
reddit_scraper/models/comment.py
reddit_scraper/models/common_utils.py
reddit_scraper/models/image.py
reddit_scraper/models/post.py
reddit_scraper/models/post_type.py
reddit_scraper/models/sorting_type.py
reddit_scraper/models/time_interval.py
reddit_scraper/models/video.py
reddit_scraper-0.0.21.dist-info/METADATA
reddit_scraper-0.0.21.dist-info/WHEEL
reddit_scraper-0.0.21.dist-info/top_level.txt
reddit_scraper-0.0.21.dist-info/RECORD
