Metadata-Version: 2.1
Name: reddit-scraper
Version: 0.0.21
Summary: reddit_scraper
Home-page: https://github.com/kkristof200/py_reddit_scraper
Author: Kristof
License: UNKNOWN
Platform: UNKNOWN
Classifier: Programming Language :: Python :: 3
Classifier: License :: OSI Approved :: MIT License
Classifier: Operating System :: OS Independent
Requires-Python: >=3.5
Requires-Dist: jsoncodable (>=0.1.7)
Requires-Dist: kcu (>=0.0.68)
